koda_knitout/Dependency_Viewer.py
koda_knitout/__about__.py
koda_knitout/__init__.py
koda_knitout/koda_optimizer.py
koda_knitout/carriage_pass_dependencies/Carriage_Pass_Dependency_Graph_Generator.py
koda_knitout/carriage_pass_dependencies/Carriage_Pass_Dependency_Viewer.py
koda_knitout/carriage_pass_dependencies/__init__.py
koda_knitout/knitout_dependencies/Knitout_Dependency_Graph_Generator.py
koda_knitout/knitout_dependencies/Knitout_Dependency_Viewer.py
koda_knitout/knitout_dependencies/__init__.py
koda_knitout/knitout_dependencies/knitout_depenendencies.py
koda_knitout/machine_state_requirements/Machine_State_Requirement.py
koda_knitout/machine_state_requirements/__init__.py
koda_knitout/machine_state_requirements/machine_setting_injection.py
koda_knitout-0.0.2.dist-info/METADATA
koda_knitout-0.0.2.dist-info/WHEEL
koda_knitout-0.0.2.dist-info/licenses/LICENSE
koda_knitout-0.0.2.dist-info/RECORD
